blang/__init__.py
blang/__main__.py
blang/cli.py
blang/exceptions.py
blang/matcher.py
blang/parser.py
blang/tokeniser.py
blang/compiler/__init__.py
blang/compiler/compiler.py
blang/compiler/entry.asm
blang/compiler/entry.o
blang/compiler/io.asm
blang/compiler/io.o
blang/compiler/precompiler.py
blang/compiler/types.py
blang-0.1.3.dist-info/METADATA
blang-0.1.3.dist-info/WHEEL
blang-0.1.3.dist-info/entry_points.txt
blang-0.1.3.dist-info/licenses/LICENSE
blang-0.1.3.dist-info/RECORD
