Metadata-Version: 2.4
Name: blang
Version: 0.1.3
Summary: A compiler for burb lang.
License-File: LICENSE
Requires-Python: >=3.12
Requires-Dist: click>=8.1.8
